{
  "start": {
    "next": "intro",
    "content": "main/start"
  },
  "pages": {
    "intro": {
      "content": "main/intro",
      "next": "fathergoing"
    },
    "fathergoing": {
      "content": "homeintro/fathergoing",
      "options": [
        "intro@dadrunaway",
        "intro@dadbegtostay",
        "intro@dadacceptgone",
        "dadfollow"
      ]
    },
    "intro@dadrunaway": {
      "content": "homeintro/runaway",
      "next": "ontherun"
    },
    "intro@dadbegtostay": {
      "content": "homeintro/dadbegtostay",
      "next": "dadisgone"
    },
    "dadfollow": {
      "content": "dadfollow/start",
      "next": "followingdad"
    },
    "intro@dadacceptgone": {
      "content": "homeintro/dadacceptgone",
      "next": "dadisgone"
    },
    "dadisgone": {
      "content": "homeintro/dadisgone",
      "options": [
        "tobabayaga@path",
        "tobabayaga@bush"
      ]
    },
    "tobabayaga@path": {
      "content": "tobabayaga/path",
      "options": [
        "bandit@run",
        "bandit@fight"
      ]
    },
    "tobabayaga@bush": {
      "content": "tobabayaga/bush",
      "next": "babayaga@arrive"
    },
    "bandit@run": {
      "content": "tobabayaga/banditrun",
      "next": "babayaga@arrive"
    },
    "bandit@fight": {
      "content": "tobabayaga/banditfight",
      "options": [
        "bandit@punch",
        "bandit@kick"
      ]
    },
    "bandit@punch": {
      "content": "tobabayaga/banditpunch",
      "next": "die"
    },
    "bandit@kick": {
      "content": "tobabayaga/banditrun",
      "next": "babayaga@arrive"
    },
    "ontherun": {
      "content": "ontherun/intro",
      "options": [
        "ontherun@cave",
        "ontherun@tree",
        "ontherun@sewer"
      ]
    },
    "ontherun@tree": {
      "content": "ontherun/tree",
      "next": "die"
    },
    "ontherun@sewer": {
      "content": "ontherun/sewer",
      "next": "dadisgone"
    },
    "ontherun@cave": {
      "content": "ontherun/cave",
      "next": "ontherun@weirdsteps"
    },
    "ontherun@weirdsteps": {
      "content": "ontherun/weirdsteps",
      "options": [
        "ontherun@downthesteps",
        "ontherun@stayincave"
      ]
    },
    "ontherun@stayincave": {
      "content": "ontherun/stayincave",
      "next": "dadisgone"
    },
    "ontherun@downthesteps": {
      "content": "ontherun/spothouse",
      "options": [
        "wizardhouse@enterhouse",
        "ontherun@hidefromhouse"
      ]
    },
    "ontherun@hidefromhouse": {
      "content": "ontherun/hidefromhouse",
      "options": [
        "wizardhouse@enterhouse",
        "wizardhouse@enterhouse"
      ]
    },
    "wizardhouse@enterhouse": {
      "content": "wizardhouse/enterhouse",
      "options": [
        "wizardhouse@attemptattack",
        "wizardhouse@listentowizard"
      ]
    },
    "wizardhouse@attemptattack": {
      "content": "wizardhouse/attemptattack",
      "next": "die"
    },
    "wizardhouse@listentowizard": {
      "content": "wizardhouse/listentowizard",
      "options": [
        "wizardhouse@becomeapprentice",
        "wizardhouse@begtofight"
      ]
    },
    "wizardhouse@begtofight": {
      "content": "wizardhouse/begtofight",
      "next": "babayaga@arrive"
    },
    "wizardhouse@becomeapprentice": {
      "content": "wizardhouse/becomeapprentice",
      "next": "babayagafight@arrive"
    },
    "babayagafight@arrive": {
      "content": "wizardhouse/arrivebabayaga",
      "options": [
        "babayagafight@enterhouse",
        "babayagafight@waitoutside"
      ]
    },
    "babayagafight@waitoutside": {
      "content": "wizardhouse/waitoutsidebabayaga",
      "next": "die"
    },
    "babayagafight@enterhouse": {
      "content": "wizardhouse/enterhousebabayaga",
      "options": [
        "babayagafight@explorehouse",
        "babayagafight@destroy"
      ]
    },
    "babayagafight@explorehouse": {
      "content": "wizardhouse/explorehousebabayaga",
      "options": [
        "die",
        "babayagafight@hidenexplore",
        "babayagafight@candleonbabayaga"
      ]
    },
    "babayagafight@hidenexplore": {
      "content": "wizardhouse/hidenexplore",
      "options": [
        "die",
        "babayagafight@candleonbabayaga",
        "babayagafight@punchbabayaga"
      ]
    },
    "babayagafight@punchbabayaga": {
      "content": "wizardhouse/punchbabayaga",
      "next": "win"
    },
    "babayagafight@candleonbabayaga": {
      "content": "wizardhouse/candleonbabayaga",
      "next": "win"
    },
    "babayagafight@destroy": {
      "content": "wizardhouse/destroyhousebabayaga",
      "next": "die"
    },
    "babayaga@arrive": {
      "content": "babayaga/arrive",
      "options": [
        "babayaga@hide",
        "babayaga@introduce"
      ]
    },
    "babayaga@hide": {
      "content": "babayaga/hide",
      "options": [
        "babayaga@discover@whimper",
        "babayaga@introduce"
      ]
    },
    "babayaga@discover@whimper": {
      "content": "babayaga/whimper",
      "next": "die"
    },
    "babayaga@introduce": {
      "content": "babayaga/introduce",
      "options": [
        "babayaga@accept-tasks",
        "babayaga@deny-tasks"
      ]
    },
    "babayaga@deny-tasks": {
      "content": "babayaga/refusetasks",
      "next": "die"
    },
    "babayaga@accept-tasks": {
      "content": "babayaga/accept-tasks",
      "options": [
        "babayaga@supper@lefthand",
        "babayaga@supper@righthand"
      ]
    },
    "babayaga@supper@lefthand": {
      "content": "babayaga/supperdrop",
      "next": "die"
    },
    "babayaga@supper@righthand": {
      "content": "babayaga/righthand",
      "next": "babayaga@day2"
    },
    "babayaga@day2": {
      "content": "babayaga/tidyyard",
      "options": [
        "babayaga@failtask",
        "babayaga@d2@rake"
      ]
    },
    "babayaga@d2@rake": {
      "content": "babayaga/cleanhut",
      "options": [
        "babayaga@failtask",
        "babayaga@d2@tidypots"
      ]
    },
    "babayaga@d2@tidypots": {
      "content": "babayaga/tidypots",
      "options": [
        "babayaga@failtask",
        "babayaga@d2@sortoutseeds"
      ]
    },
    "babayaga@d2@sortoutseeds": {
      "content": "babayaga/sortseeds",
      "options": [
        "babayaga@failtask",
        "babayaga@d2@usedollseeds"
      ]
    },
    "babayaga@d2@usedollseeds": {
      "content": "babayaga/doneseeds",
      "next": "babayaga@d3@soup"
    },
    "babayaga@d3@soup": {
      "content": "babayaga/makepeasoup",
      "options": [
        "babayaga@failtask",
        "babayaga@d3@askdollforhelp"
      ]
    },
    "babayaga@d3@askdollforhelp": {
      "content": "babayaga/sortedpeas",
      "options": [
        "babayaga@d3@bucketfilled",
        "babayaga@failtask"
      ]
    },
    "babayaga@d3@bucketfilled": {
      "content": "babayaga/bucketfilled",
      "next": "babayaga@d4@foundstars"
    },
    "babayaga@d4@foundstars": {
      "content": "babayaga/foundstars",
      "next": "win"
    },
    "babayaga@failtask": {
      "next": "die",
      "content": "babayaga/failtask"
    },
    "die": {
      "content": "main/die"
    },
    "win": {
      "content": "main/win"
    }
  }
}
